{
	"name": "AzureSqlRAWPRO",
	"properties": {
		"linkedServiceName": {
			"referenceName": "AzureSqlDatabase1",
			"type": "LinkedServiceReference"
		},
		"parameters": {
			"schema": {
				"type": "string"
			},
			"table": {
				"type": "string"
			}
		},
		"folder": {
			"name": "PRUEB"
		},
		"annotations": [],
		"type": "AzureSqlTable",
		"schema": [],
		"typeProperties": {
			"schema": {
				"value": "@dataset().schema",
				"type": "Expression"
			},
			"table": {
				"value": "@dataset().table",
				"type": "Expression"
			}
		}
	}
}